nocaplang/__init__.py
nocaplang/compiler.py
nocaplang/error_formatter.py
nocaplang/cli/__init__.py
nocaplang/cli/main.py
nocaplang/codegen/__init__.py
nocaplang/codegen/cpp_generator.py
nocaplang/codegen/java_generator.py
nocaplang/lexer/__init__.py
nocaplang/lexer/lexer.py
nocaplang/lexer/token.py
nocaplang/optimizer/__init__.py
nocaplang/optimizer/optimizer.py
nocaplang/parser/__init__.py
nocaplang/parser/ast_nodes.py
nocaplang/parser/examples.py
nocaplang/parser/parser.py
nocaplang/repl/__init__.py
nocaplang/repl/repl.py
nocaplang/semantic/__init__.py
nocaplang/semantic/analyzer.py
nocaplang/semantic/types.py
nocaplang/stdlib/__init__.py
nocaplang/stdlib/nocaplang_stdlib.hpp
nocaplang-1.0.0.dist-info/licenses/LICENSE
nocaplang-1.0.0.dist-info/METADATA
nocaplang-1.0.0.dist-info/WHEEL
nocaplang-1.0.0.dist-info/entry_points.txt
nocaplang-1.0.0.dist-info/top_level.txt
nocaplang-1.0.0.dist-info/RECORD
