Metadata-Version: 2.4
Name: nocaplang
Version: 1.0.0
Summary: A Gen Z slang-based programming language that compiles to C++. No cap fr fr! 🔥
Home-page: https://nocaplang.com
Author: Soumik Mukherjee
License: MIT
Project-URL: Homepage, https://nocaplang.com
Project-URL: Documentation, https://nocaplang.com/docs
Project-URL: Playground, https://nocaplang.com/playground
Keywords: programming-language,compiler,transpiler,gen-z,slang,cpp,java,education,fun
Classifier: Development Status :: 4 - Beta
Classifier: Intended Audience :: Developers
Classifier: Intended Audience :: Education
Classifier: Topic :: Software Development :: Compilers
Classifier: Topic :: Software Development :: Code Generators
Classifier: License :: OSI Approved :: MIT License
Classifier: Programming Language :: Python :: 3
Classifier: Programming Language :: Python :: 3.8
Classifier: Programming Language :: Python :: 3.9
Classifier: Programming Language :: Python :: 3.10
Classifier: Programming Language :: Python :: 3.11
Classifier: Programming Language :: Python :: 3.12
Classifier: Operating System :: OS Independent
Classifier: Natural Language :: English
Requires-Python: >=3.8
License-File: LICENSE
Provides-Extra: dev
Requires-Dist: pytest>=7.0; extra == "dev"
Requires-Dist: hypothesis>=6.0.0; extra == "dev"
Requires-Dist: black>=23.0; extra == "dev"
Dynamic: author
Dynamic: classifier
Dynamic: description
Dynamic: description-content-type
Dynamic: home-page
Dynamic: keywords
Dynamic: license
Dynamic: license-file
Dynamic: project-url
Dynamic: provides-extra
Dynamic: requires-python
Dynamic: summary
